redfishtool-1.1.8.data/scripts/redfishtool
redfishtool-1.1.8.data/scripts/redfishtool.py
redfishtoollib/AccountService.py
redfishtoollib/Chassis.py
redfishtoollib/Managers.py
redfishtoollib/ServiceRoot.py
redfishtoollib/SessionService.py
redfishtoollib/Systems.py
redfishtoollib/__init__.py
redfishtoollib/raw.py
redfishtoollib/redfishtoolMain.py
redfishtoollib/redfishtoolTransport.py
redfishtool-1.1.8.dist-info/AUTHORS.md
redfishtool-1.1.8.dist-info/LICENSE.md
redfishtool-1.1.8.dist-info/METADATA
redfishtool-1.1.8.dist-info/WHEEL
redfishtool-1.1.8.dist-info/top_level.txt
redfishtool-1.1.8.dist-info/RECORD
