Metadata-Version: 2.1
Name: redfishtool
Version: 1.1.8
Summary: Redfishtool package and command-line client
Home-page: https://github.com/DMTF/Redfishtool
Download-URL: https://github.com/DMTF/Redfishtool/archive/1.1.5.tar.gz
Author: DMTF, https://www.dmtf.org/standards/feedback
License: BSD 3-clause "New" or "Revised License"
Keywords: Redfish
Classifier: Development Status :: 5 - Production/Stable
Classifier: License :: OSI Approved :: BSD License
Classifier: Programming Language :: Python :: 3.4
Classifier: Topic :: Software Development :: Libraries :: Python Modules
Classifier: Topic :: Communications
License-File: LICENSE.md
License-File: AUTHORS.md
Requires-Dist: python-dateutil
Requires-Dist: requests
